teg_CCC.py
teg_CCC-0.0.3.dist-info/LICENSE
teg_CCC-0.0.3.dist-info/METADATA
teg_CCC-0.0.3.dist-info/WHEEL
teg_CCC-0.0.3.dist-info/top_level.txt
teg_CCC-0.0.3.dist-info/RECORD
