Metadata-Version: 2.1
Name: teg-CCC
Version: 0.0.3
Summary: Estimate the true number of clusters for k-means clustering using the Cluster Consistency Criterion (CCC).
Author-email: "Thomas E. Gladwin" <thomasgladwin@hotmail.com>
Project-URL: Homepage, https://tegladwin.com
Project-URL: Bug Tracker, https://github.com/thomasgladwin/teg_CCC
Classifier: Programming Language :: Python :: 3
Classifier: License :: OSI Approved :: MIT License
Classifier: Operating System :: OS Independent
Requires-Python: >=3.9
License-File: LICENSE
Requires-Dist: numpy
Requires-Dist: scikit-learn
